{"result":{"status":{"code":0,"msg":null},"data":{"match":{"id":"o_987838","type_name":"\u82f1\u8d85","type_id":"8","status":3,"home_name_cn":"\u83b1\u65af\u7279\u57ce","away_name_cn":"\u66fc\u8054","home_id":"o_13","away_id":"o_1","home_score":"0","away_score":"1","home_half":"0","away_half":"1","home_logo_big":"http:\/\/www.sinaimg.cn\/lf\/sports\/logo85\/92.png","away_logo_big":"http:\/\/www.sinaimg.cn\/lf\/sports\/logo85\/52.png","home_color":"http:\/\/www.sinaimg.cn\/lf\/sports\/kits\/2015\/home\/92.png","away_color":"http:\/\/www.sinaimg.cn\/lf\/sports\/kits\/2015\/away\/52.png"},"stats":{"away":[{"player_name":"David De Gea","player_name_cn":"\u5fb7\u8d6b\u4e9a","league_id":"2015","id":"823812","match_id":"987838","team_id":"1","player_id":"51940","position_id":"1","shirt_number":"1","total_scoring_att":"0","ontarget_scoring_att":"0","goals":"0","goal_assist":"0","total_att_assist":"0","total_contest":"0","won_contest":"0","fouls":"0","was_fouled":"0","total_clearance":"0","saves":"6","won_tackle":"0","total_tackle":"0","accurate_pass":"15","total_pass":"20","mins_played":"90","modify_time":"190204 060401","scoring_persent":0,"status":"z","status_cn":"\u9996\u53d1","position_cn":"\u95e8","position_long_cn":"\u95e8\u5c06"},{"player_name":"Luke Shaw","player_name_cn":"\u5362\u514b\u8096","league_id":"2018","id":"823815","match_id":"987838","team_id":"1","player_id":"106760","position_id":"2","shirt_number":"23","total_scoring_att":"0","ontarget_scoring_att":"0","goals":"0","goal_assist":"0","total_att_assist":"3","total_contest":"2","won_contest":"2","fouls":"2","was_fouled":"0","total_clearance":"1","saves":"0","won_tackle":"2","total_tackle":"3","accurate_pass":"55","total_pass":"68","mins_played":"90","modify_time":"190204 060401","scoring_persent":0,"status":"z","status_cn":"\u9996\u53d1","position_cn":"\u536b","position_long_cn":"\u540e\u536b"},{"player_name":"Victor Lindel\u00f6f","player_name_cn":"\u6797\u5fb7\u6d1b\u592b","league_id":"2015","id":"823814","match_id":"987838","team_id":"1","player_id":"184667","position_id":"2","shirt_number":"2","total_scoring_att":"0","ontarget_scoring_att":"0","goals":"0","goal_assist":"0","total_att_assist":"0","total_contest":"0","won_contest":"0","fouls":"0","was_fouled":"1","total_clearance":"4","saves":"0","won_tackle":"1","total_tackle":"1","accurate_pass":"45","total_pass":"47","mins_played":"90","modify_time":"190204 060401","scoring_persent":0,"status":"z","status_cn":"\u9996\u53d1","position_cn":"\u536b","position_long_cn":"\u540e\u536b"},{"player_name":"Ashley Young","player_name_cn":"\u963f\u4ec0\u5229-\u626c","league_id":"2010","id":"823816","match_id":"987838","team_id":"1","player_id":"18892","position_id":"2","shirt_number":"18","total_scoring_att":"0","ontarget_scoring_att":"0","goals":"0","goal_assist":"0","total_att_assist":"2","total_contest":"0","won_contest":"0","fouls":"1","was_fouled":"1","total_clearance":"4","saves":"0","won_tackle":"1","total_tackle":"1","accurate_pass":"43","total_pass":"59","mins_played":"90","modify_time":"190204 060401","scoring_persent":0,"status":"z","status_cn":"\u9996\u53d1","position_cn":"\u536b","position_long_cn":"\u540e\u536b"},{"player_name":"Eric Bailly","player_name_cn":"Eric Bailly","league_id":"2014","id":"823813","match_id":"987838","team_id":"1","player_id":"197365","position_id":"2","shirt_number":"3","total_scoring_att":"0","ontarget_scoring_att":"0","goals":"0","goal_assist":"0","total_att_assist":"0","total_contest":"1","won_contest":"1","fouls":"0","was_fouled":"0","total_clearance":"5","saves":"0","won_tackle":"0","total_tackle":"0","accurate_pass":"31","total_pass":"39","mins_played":"90","modify_time":"190204 060401","scoring_persent":0,"status":"z","status_cn":"\u9996\u53d1","position_cn":"\u536b","position_long_cn":"\u540e\u536b"},{"player_name":"Alexis S\u00e1nchez","player_name_cn":"A-\u6851\u5207\u65af","league_id":"2011","id":"823821","match_id":"987838","team_id":"1","player_id":"37265","position_id":"3","shirt_number":"7","total_scoring_att":"0","ontarget_scoring_att":"0","goals":"0","goal_assist":"0","total_att_assist":"0","total_contest":"1","won_contest":"1","fouls":"0","was_fouled":"0","total_clearance":"0","saves":"0","won_tackle":"1","total_tackle":"1","accurate_pass":"23","total_pass":"30","mins_played":"67","modify_time":"190204 060401","scoring_persent":0,"status":"z","status_cn":"\u9996\u53d1","position_cn":"\u4e2d","position_long_cn":"\u4e2d\u573a"},{"player_name":"Ander Herrera","player_name_cn":"\u57c3\u96f7\u62c9","league_id":"2018","id":"823818","match_id":"987838","team_id":"1","player_id":"59846","position_id":"3","shirt_number":"21","total_scoring_att":"0","ontarget_scoring_att":"0","goals":"0","goal_assist":"0","total_att_assist":"2","total_contest":"4","won_contest":"3","fouls":"0","was_fouled":"1","total_clearance":"2","saves":"0","won_tackle":"1","total_tackle":"5","accurate_pass":"52","total_pass":"61","mins_played":"90","modify_time":"190204 060401","scoring_persent":0,"status":"z","status_cn":"\u9996\u53d1","position_cn":"\u4e2d","position_long_cn":"\u4e2d\u573a"},{"player_name":"Paul Pogba","player_name_cn":"\u535a\u683c\u5df4","league_id":"2017","id":"823819","match_id":"987838","team_id":"1","player_id":"74208","position_id":"3","shirt_number":"6","total_scoring_att":"0","ontarget_scoring_att":"0","goals":"0","goal_assist":"1","total_att_assist":"2","total_contest":"3","won_contest":"3","fouls":"0","was_fouled":"1","total_clearance":"0","saves":"0","won_tackle":"1","total_tackle":"2","accurate_pass":"60","total_pass":"71","mins_played":"90","modify_time":"190204 060401","scoring_persent":0,"status":"z","status_cn":"\u9996\u53d1","position_cn":"\u4e2d","position_long_cn":"\u4e2d\u573a"},{"player_name":"Jesse Lingard","player_name_cn":"\u6770\u897f-\u6797\u52a0\u5fb7","league_id":"2017","id":"823820","match_id":"987838","team_id":"1","player_id":"109322","position_id":"3","shirt_number":"14","total_scoring_att":"2","ontarget_scoring_att":"1","goals":"0","goal_assist":"0","total_att_assist":"0","total_contest":"1","won_contest":"1","fouls":"2","was_fouled":"1","total_clearance":"0","saves":"0","won_tackle":"2","total_tackle":"2","accurate_pass":"33","total_pass":"38","mins_played":"89","modify_time":"190204 060401","scoring_persent":"50%","status":"z","status_cn":"\u9996\u53d1","position_cn":"\u4e2d","position_long_cn":"\u4e2d\u573a"},{"player_name":"Nemanja Matic","player_name_cn":"\u9a6c\u8482\u5947","league_id":"2013","id":"823817","match_id":"987838","team_id":"1","player_id":"62398","position_id":"3","shirt_number":"31","total_scoring_att":"0","ontarget_scoring_att":"0","goals":"0","goal_assist":"0","total_att_assist":"0","total_contest":"1","won_contest":"1","fouls":"3","was_fouled":"2","total_clearance":"2","saves":"0","won_tackle":"1","total_tackle":"1","accurate_pass":"45","total_pass":"60","mins_played":"90","modify_time":"190204 060401","scoring_persent":0,"status":"z","status_cn":"\u9996\u53d1","position_cn":"\u4e2d","position_long_cn":"\u4e2d\u573a"},{"player_name":"Marcus Rashford","player_name_cn":"\u62c9\u4ec0\u798f\u5fb7","league_id":"2016","id":"823822","match_id":"987838","team_id":"1","player_id":"176297","position_id":"4","shirt_number":"10","total_scoring_att":"5","ontarget_scoring_att":"3","goals":"1","goal_assist":"0","total_att_assist":"0","total_contest":"2","won_contest":"1","fouls":"0","was_fouled":"2","total_clearance":"3","saves":"0","won_tackle":"0","total_tackle":"0","accurate_pass":"16","total_pass":"19","mins_played":"78","modify_time":"190204 060401","scoring_persent":"60%","status":"z","status_cn":"\u9996\u53d1","position_cn":"\u950b","position_long_cn":"\u524d\u950b"},{"player_name":"Phil Jones","player_name_cn":"\u83f2\u5c14-\u743c\u65af","league_id":"2017","id":"823829","match_id":"987838","team_id":"1","player_id":"76359","position_id":"5","shirt_number":"4","total_scoring_att":"0","ontarget_scoring_att":"0","goals":"0","goal_assist":"0","total_att_assist":"0","total_contest":"0","won_contest":"0","fouls":"0","was_fouled":"0","total_clearance":"1","saves":"0","won_tackle":"0","total_tackle":"0","accurate_pass":"0","total_pass":"0","mins_played":"1","modify_time":"190204 060401","scoring_persent":0,"status":"t","status_cn":"\u66ff\u8865","position_cn":"\u66ff","position_long_cn":"\u66ff\u8865"},{"player_name":"Sergio Romero","player_name_cn":"\u7f57\u6885\u7f57","league_id":"2013","id":"823825","match_id":"987838","team_id":"1","player_id":"42899","position_id":"5","shirt_number":"22","total_scoring_att":"0","ontarget_scoring_att":"0","goals":"0","goal_assist":"0","total_att_assist":"0","total_contest":"0","won_contest":"0","fouls":"0","was_fouled":"0","total_clearance":"0","saves":"0","won_tackle":"0","total_tackle":"0","accurate_pass":"0","total_pass":"0","mins_played":"0","modify_time":"190204 060401","scoring_persent":0,"status":"t","status_cn":"\u66ff\u8865","position_cn":"\u66ff","position_long_cn":"\u66ff\u8865"},{"player_name":"Romelu Lukaku","player_name_cn":"\u5362\u5361\u5e93","league_id":"2014","id":"823827","match_id":"987838","team_id":"1","player_id":"66749","position_id":"5","shirt_number":"9","total_scoring_att":"1","ontarget_scoring_att":"1","goals":"0","goal_assist":"0","total_att_assist":"0","total_contest":"1","won_contest":"1","fouls":"0","was_fouled":"0","total_clearance":"0","saves":"0","won_tackle":"1","total_tackle":"1","accurate_pass":"4","total_pass":"8","mins_played":"12","modify_time":"190204 060401","scoring_persent":"100%","status":"t","status_cn":"\u66ff\u8865","position_cn":"\u66ff","position_long_cn":"\u66ff\u8865"},{"player_name":"Anthony Martial","player_name_cn":"\u9a6c\u590f\u5c14","league_id":"2017","id":"823828","match_id":"987838","team_id":"1","player_id":"148225","position_id":"5","shirt_number":"11","total_scoring_att":"2","ontarget_scoring_att":"1","goals":"0","goal_assist":"0","total_att_assist":"0","total_contest":"3","won_contest":"2","fouls":"1","was_fouled":"3","total_clearance":"0","saves":"0","won_tackle":"0","total_tackle":"0","accurate_pass":"9","total_pass":"13","mins_played":"23","modify_time":"190204 060401","scoring_persent":"50%","status":"t","status_cn":"\u66ff\u8865","position_cn":"\u66ff","position_long_cn":"\u66ff\u8865"},{"player_name":"Juan Mata","player_name_cn":"\u9a6c\u5854","league_id":"2018","id":"823824","match_id":"987838","team_id":"1","player_id":"43670","position_id":"5","shirt_number":"8","total_scoring_att":"0","ontarget_scoring_att":"0","goals":"0","goal_assist":"0","total_att_assist":"0","total_contest":"0","won_contest":"0","fouls":"0","was_fouled":"0","total_clearance":"0","saves":"0","won_tackle":"0","total_tackle":"0","accurate_pass":"0","total_pass":"0","mins_played":"0","modify_time":"190204 060401","scoring_persent":0,"status":"t","status_cn":"\u66ff\u8865","position_cn":"\u66ff","position_long_cn":"\u66ff\u8865"},{"player_name":"Fred","player_name_cn":"\u5f17\u96f7\u5fb7","league_id":"2018","id":"823823","match_id":"987838","team_id":"1","player_id":"101582","position_id":"5","shirt_number":"17","total_scoring_att":"0","ontarget_scoring_att":"0","goals":"0","goal_assist":"0","total_att_assist":"0","total_contest":"0","won_contest":"0","fouls":"0","was_fouled":"0","total_clearance":"0","saves":"0","won_tackle":"0","total_tackle":"0","accurate_pass":"0","total_pass":"0","mins_played":"0","modify_time":"190204 060401","scoring_persent":0,"status":"t","status_cn":"\u66ff\u8865","position_cn":"\u66ff","position_long_cn":"\u66ff\u8865"},{"player_name":"Diogo Dalot","player_name_cn":"\u8fbe\u6d1b\u7279","league_id":"2018","id":"823826","match_id":"987838","team_id":"1","player_id":"216051","position_id":"5","shirt_number":"20","total_scoring_att":"0","ontarget_scoring_att":"0","goals":"0","goal_assist":"0","total_att_assist":"0","total_contest":"0","won_contest":"0","fouls":"0","was_fouled":"0","total_clearance":"0","saves":"0","won_tackle":"0","total_tackle":"0","accurate_pass":"0","total_pass":"0","mins_played":"0","modify_time":"190204 060401","scoring_persent":0,"status":"t","status_cn":"\u66ff\u8865","position_cn":"\u66ff","position_long_cn":"\u66ff\u8865"}],"home":[{"player_name":"Kasper Schmeichel","player_name_cn":"\u8212\u6885\u5207\u5c14","league_id":"2016","id":"823794","match_id":"987838","team_id":"13","player_id":"17745","position_id":"1","shirt_number":"1","total_scoring_att":"0","ontarget_scoring_att":"0","goals":"0","goal_assist":"0","total_att_assist":"0","total_contest":"0","won_contest":"0","fouls":"0","was_fouled":"0","total_clearance":"0","saves":"5","won_tackle":"0","total_tackle":"0","accurate_pass":"10","total_pass":"19","mins_played":"90","modify_time":"190204 060401","scoring_persent":0,"status":"z","status_cn":"\u9996\u53d1","position_cn":"\u95e8","position_long_cn":"\u95e8\u5c06"},{"player_name":"Ricardo Pereira","player_name_cn":"\u4f69\u96f7\u62c9","league_id":"2018","id":"823795","match_id":"987838","team_id":"13","player_id":"111931","position_id":"2","shirt_number":"14","total_scoring_att":"1","ontarget_scoring_att":"1","goals":"0","goal_assist":"0","total_att_assist":"1","total_contest":"2","won_contest":"1","fouls":"2","was_fouled":"3","total_clearance":"0","saves":"0","won_tackle":"4","total_tackle":"4","accurate_pass":"20","total_pass":"26","mins_played":"90","modify_time":"190204 060401","scoring_persent":"100%","status":"z","status_cn":"\u9996\u53d1","position_cn":"\u536b","position_long_cn":"\u540e\u536b"},{"player_name":"Harry Maguire","player_name_cn":"\u9a6c\u76d6\u5c14","league_id":"2016","id":"823797","match_id":"987838","team_id":"13","player_id":"95658","position_id":"2","shirt_number":"15","total_scoring_att":"1","ontarget_scoring_att":"0","goals":"0","goal_assist":"0","total_att_assist":"0","total_contest":"1","won_contest":"0","fouls":"2","was_fouled":"0","total_clearance":"2","saves":"0","won_tackle":"0","total_tackle":"0","accurate_pass":"51","total_pass":"59","mins_played":"90","modify_time":"190204 060401","scoring_persent":"0%","status":"z","status_cn":"\u9996\u53d1","position_cn":"\u536b","position_long_cn":"\u540e\u536b"},{"player_name":"Jonny Evans","player_name_cn":"\u57c3\u6587\u65af","league_id":"2018","id":"823796","match_id":"987838","team_id":"13","player_id":"37642","position_id":"2","shirt_number":"6","total_scoring_att":"1","ontarget_scoring_att":"0","goals":"0","goal_assist":"0","total_att_assist":"0","total_contest":"0","won_contest":"0","fouls":"2","was_fouled":"0","total_clearance":"6","saves":"0","won_tackle":"0","total_tackle":"1","accurate_pass":"29","total_pass":"37","mins_played":"90","modify_time":"190204 060401","scoring_persent":"0%","status":"z","status_cn":"\u9996\u53d1","position_cn":"\u536b","position_long_cn":"\u540e\u536b"},{"player_name":"Ben Chilwell","player_name_cn":"\u5947\u7ef4\u5c14","league_id":"2017","id":"823798","match_id":"987838","team_id":"13","player_id":"172850","position_id":"2","shirt_number":"3","total_scoring_att":"0","ontarget_scoring_att":"0","goals":"0","goal_assist":"0","total_att_assist":"0","total_contest":"1","won_contest":"1","fouls":"0","was_fouled":"1","total_clearance":"4","saves":"0","won_tackle":"2","total_tackle":"2","accurate_pass":"35","total_pass":"50","mins_played":"90","modify_time":"190204 060401","scoring_persent":0,"status":"z","status_cn":"\u9996\u53d1","position_cn":"\u536b","position_long_cn":"\u540e\u536b"},{"player_name":"Nampalys Mendy","player_name_cn":"\u95e8\u8fea","league_id":"2017","id":"823802","match_id":"987838","team_id":"13","player_id":"86881","position_id":"3","shirt_number":"24","total_scoring_att":"0","ontarget_scoring_att":"0","goals":"0","goal_assist":"0","total_att_assist":"2","total_contest":"1","won_contest":"1","fouls":"1","was_fouled":"1","total_clearance":"1","saves":"0","won_tackle":"0","total_tackle":"0","accurate_pass":"42","total_pass":"46","mins_played":"84","modify_time":"190204 060401","scoring_persent":0,"status":"z","status_cn":"\u9996\u53d1","position_cn":"\u4e2d","position_long_cn":"\u4e2d\u573a"},{"player_name":"Wilfred Ndidi","player_name_cn":"\u6069\u8fea\u8fea","league_id":"2017","id":"823803","match_id":"987838","team_id":"13","player_id":"203341","position_id":"3","shirt_number":"25","total_scoring_att":"2","ontarget_scoring_att":"0","goals":"0","goal_assist":"0","total_att_assist":"0","total_contest":"3","won_contest":"2","fouls":"1","was_fouled":"0","total_clearance":"1","saves":"0","won_tackle":"0","total_tackle":"3","accurate_pass":"40","total_pass":"48","mins_played":"90","modify_time":"190204 060401","scoring_persent":"0%","status":"z","status_cn":"\u9996\u53d1","position_cn":"\u4e2d","position_long_cn":"\u4e2d\u573a"},{"player_name":"James Maddison","player_name_cn":"James Maddison","league_id":"2015","id":"823799","match_id":"987838","team_id":"13","player_id":"172780","position_id":"3","shirt_number":"10","total_scoring_att":"4","ontarget_scoring_att":"1","goals":"0","goal_assist":"0","total_att_assist":"3","total_contest":"4","won_contest":"4","fouls":"0","was_fouled":"1","total_clearance":"0","saves":"0","won_tackle":"0","total_tackle":"1","accurate_pass":"21","total_pass":"32","mins_played":"62","modify_time":"190204 060401","scoring_persent":"25%","status":"z","status_cn":"\u9996\u53d1","position_cn":"\u4e2d","position_long_cn":"\u4e2d\u573a"},{"player_name":"Harvey Barnes","player_name_cn":"\u5df4\u6069\u65af","league_id":"2016","id":"823801","match_id":"987838","team_id":"13","player_id":"201666","position_id":"3","shirt_number":"19","total_scoring_att":"3","ontarget_scoring_att":"1","goals":"0","goal_assist":"0","total_att_assist":"2","total_contest":"3","won_contest":"2","fouls":"2","was_fouled":"0","total_clearance":"1","saves":"0","won_tackle":"0","total_tackle":"1","accurate_pass":"23","total_pass":"31","mins_played":"90","modify_time":"190204 060401","scoring_persent":"33.3%","status":"z","status_cn":"\u9996\u53d1","position_cn":"\u4e2d","position_long_cn":"\u4e2d\u573a"},{"player_name":"Demarai Gray","player_name_cn":"\u5fb7\u9a6c\u83b1-\u683c\u96f7","league_id":"2016","id":"823800","match_id":"987838","team_id":"13","player_id":"172632","position_id":"3","shirt_number":"7","total_scoring_att":"1","ontarget_scoring_att":"0","goals":"0","goal_assist":"0","total_att_assist":"1","total_contest":"0","won_contest":"0","fouls":"1","was_fouled":"0","total_clearance":"0","saves":"0","won_tackle":"0","total_tackle":"0","accurate_pass":"18","total_pass":"21","mins_played":"74","modify_time":"190204 060401","scoring_persent":"0%","status":"z","status_cn":"\u9996\u53d1","position_cn":"\u4e2d","position_long_cn":"\u4e2d\u573a"},{"player_name":"Jamie Vardy","player_name_cn":"\u74e6\u5c14\u8fea","league_id":"2017","id":"823804","match_id":"987838","team_id":"13","player_id":"101668","position_id":"4","shirt_number":"9","total_scoring_att":"3","ontarget_scoring_att":"2","goals":"0","goal_assist":"0","total_att_assist":"1","total_contest":"1","won_contest":"0","fouls":"1","was_fouled":"1","total_clearance":"0","saves":"0","won_tackle":"0","total_tackle":"0","accurate_pass":"12","total_pass":"18","mins_played":"90","modify_time":"190204 060401","scoring_persent":"66.7%","status":"z","status_cn":"\u9996\u53d1","position_cn":"\u950b","position_long_cn":"\u524d\u950b"},{"player_name":"Kelechi Iheanacho","player_name_cn":"\u4f0a\u6d77\u4e9a\u7eb3\u4e54","league_id":"2018","id":"823809","match_id":"987838","team_id":"13","player_id":"173515","position_id":"5","shirt_number":"8","total_scoring_att":"0","ontarget_scoring_att":"0","goals":"0","goal_assist":"0","total_att_assist":"0","total_contest":"1","won_contest":"0","fouls":"0","was_fouled":"0","total_clearance":"0","saves":"0","won_tackle":"0","total_tackle":"0","accurate_pass":"4","total_pass":"4","mins_played":"6","modify_time":"190204 060401","scoring_persent":0,"status":"t","status_cn":"\u66ff\u8865","position_cn":"\u66ff","position_long_cn":"\u66ff\u8865"},{"player_name":"Christian Fuchs","player_name_cn":"C-\u798f\u514b\u65af","league_id":"2016","id":"823811","match_id":"987838","team_id":"13","player_id":"37402","position_id":"5","shirt_number":"28","total_scoring_att":"0","ontarget_scoring_att":"0","goals":"0","goal_assist":"0","total_att_assist":"0","total_contest":"0","won_contest":"0","fouls":"0","was_fouled":"0","total_clearance":"0","saves":"0","won_tackle":"0","total_tackle":"0","accurate_pass":"0","total_pass":"0","mins_played":"0","modify_time":"190204 060401","scoring_persent":0,"status":"t","status_cn":"\u66ff\u8865","position_cn":"\u66ff","position_long_cn":"\u66ff\u8865"},{"player_name":"Wes Morgan","player_name_cn":"\u6469\u6839","league_id":"2018","id":"823806","match_id":"987838","team_id":"13","player_id":"15033","position_id":"5","shirt_number":"5","total_scoring_att":"0","ontarget_scoring_att":"0","goals":"0","goal_assist":"0","total_att_assist":"0","total_contest":"0","won_contest":"0","fouls":"0","was_fouled":"0","total_clearance":"0","saves":"0","won_tackle":"0","total_tackle":"0","accurate_pass":"0","total_pass":"0","mins_played":"0","modify_time":"190204 060401","scoring_persent":0,"status":"t","status_cn":"\u66ff\u8865","position_cn":"\u66ff","position_long_cn":"\u66ff\u8865"},{"player_name":"Hamza Choudhury","player_name_cn":"Hamza Choudhury","league_id":"2016","id":"823805","match_id":"987838","team_id":"13","player_id":"197469","position_id":"5","shirt_number":"38","total_scoring_att":"0","ontarget_scoring_att":"0","goals":"0","goal_assist":"0","total_att_assist":"0","total_contest":"0","won_contest":"0","fouls":"0","was_fouled":"0","total_clearance":"0","saves":"0","won_tackle":"0","total_tackle":"0","accurate_pass":"0","total_pass":"0","mins_played":"0","modify_time":"190204 060401","scoring_persent":0,"status":"t","status_cn":"\u66ff\u8865","position_cn":"\u66ff","position_long_cn":"\u66ff\u8865"},{"player_name":"Shinji Okazaki","player_name_cn":"\u5188\u5d0e\u614e\u53f8","league_id":"2012","id":"823808","match_id":"987838","team_id":"13","player_id":"78412","position_id":"5","shirt_number":"20","total_scoring_att":"0","ontarget_scoring_att":"0","goals":"0","goal_assist":"0","total_att_assist":"0","total_contest":"0","won_contest":"0","fouls":"1","was_fouled":"0","total_clearance":"0","saves":"0","won_tackle":"1","total_tackle":"1","accurate_pass":"4","total_pass":"7","mins_played":"16","modify_time":"190204 060401","scoring_persent":0,"status":"t","status_cn":"\u66ff\u8865","position_cn":"\u66ff","position_long_cn":"\u66ff\u8865"},{"player_name":"Danny Ward","player_name_cn":"\u6c83\u5fb7","league_id":"2017","id":"823810","match_id":"987838","team_id":"13","player_id":"95463","position_id":"5","shirt_number":"12","total_scoring_att":"0","ontarget_scoring_att":"0","goals":"0","goal_assist":"0","total_att_assist":"0","total_contest":"0","won_contest":"0","fouls":"0","was_fouled":"0","total_clearance":"0","saves":"0","won_tackle":"0","total_tackle":"0","accurate_pass":"0","total_pass":"0","mins_played":"0","modify_time":"190204 060401","scoring_persent":0,"status":"t","status_cn":"\u66ff\u8865","position_cn":"\u66ff","position_long_cn":"\u66ff\u8865"},{"player_name":"Rachid Ghezzal","player_name_cn":"\u5409\u624e\u5c14","league_id":"2018","id":"823807","match_id":"987838","team_id":"13","player_id":"115858","position_id":"5","shirt_number":"31","total_scoring_att":"1","ontarget_scoring_att":"1","goals":"0","goal_assist":"0","total_att_assist":"0","total_contest":"3","won_contest":"2","fouls":"1","was_fouled":"1","total_clearance":"0","saves":"0","won_tackle":"0","total_tackle":"1","accurate_pass":"18","total_pass":"21","mins_played":"28","modify_time":"190204 060401","scoring_persent":"100%","status":"t","status_cn":"\u66ff\u8865","position_cn":"\u66ff","position_long_cn":"\u66ff\u8865"}]}}}}